[{"areaCode": "814", "bounds": [[-80.5265, 39.7215], [-77.1808, 42.5154]], "continent": "north-america", "country": "united-states-of-america", "subdivision": "pennsylvania"}, {"areaCode": "412-878", "bounds": [[-80.304, 40.2071], [-79.6719, 40.6141]], "continent": "north-america", "country": "united-states-of-america", "subdivision": "pennsylvania"}, {"areaCode": "717", "bounds": [[-78.3803, 39.7198], [-75.9182, 40.8473]], "continent": "north-america", "country": "united-states-of-america", "subdivision": "pennsylvania"}, {"areaCode": "724-878", "bounds": [[-80.5197, 39.7206], [-78.8081, 41.6449]], "continent": "north-america", "country": "united-states-of-america", "subdivision": "pennsylvania"}, {"areaCode": "272-570", "bounds": [[-78.0933, 40.4954], [-74.6895, 42.0018]], "continent": "north-america", "country": "united-states-of-america", "subdivision": "pennsylvania"}, {"areaCode": "484-610", "bounds": [[-76.259, 39.7215], [-75.0619, 40.9483]], "continent": "north-america", "country": "united-states-of-america", "subdivision": "pennsylvania"}, {"areaCode": "215-267-445", "bounds": [[-75.5937, 39.8659], [-74.7215, 40.4993]], "continent": "north-america", "country": "united-states-of-america", "subdivision": "pennsylvania"}]