[{"areaCode": 39, "bounds": [[-331.8894, -31.63623053262573], [-328.94847675558475, -29.4966]], "continent": "africa", "country": "south-africa", "subdivision": "eastern-cape"}, {"areaCode": 40, "bounds": [[-333.5014, -33.646813607312076], [-332.3384354755152, -32.3274]], "continent": "africa", "country": "south-africa", "subdivision": "eastern-cape"}, {"areaCode": 41, "bounds": [[-334.8078, -34.317982171308046], [-333.3269351547159, -33.4083]], "continent": "africa", "country": "south-africa", "subdivision": "eastern-cape"}, {"areaCode": 42, "bounds": [[-336.605, -34.41840284744896], [-333.7149, -32.3067]], "continent": "africa", "country": "south-africa", "subdivision": "eastern-cape"}, {"areaCode": 43, "bounds": [[-332.8422, -33.42521389097925], [-331.41724148482075, -32.1909]], "continent": "africa", "country": "south-africa", "subdivision": "eastern-cape"}, {"areaCode": 44, "bounds": [[-338.3598, -34.51348639919316], [-336.1072359, -32.7276]], "continent": "africa", "country": "south-africa", "subdivision": "eastern-cape"}, {"areaCode": 45, "bounds": [[-333.9668, -32.7663], [-331.3019, -30.4923]], "continent": "africa", "country": "south-africa", "subdivision": "eastern-cape"}, {"areaCode": 46, "bounds": [[-334.1127, -33.92142033973756], [-332.7031978962913, -32.2717]], "continent": "africa", "country": "south-africa", "subdivision": "eastern-cape"}, {"areaCode": 47, "bounds": [[-333.0336, -32.79607188698312], [-330.1127012449957, -30.8298]], "continent": "africa", "country": "south-africa", "subdivision": "eastern-cape"}, {"areaCode": 48, "bounds": [[-334.798401, -32.5379], [-333.8316128, -31.3267]], "continent": "africa", "country": "south-africa", "subdivision": "eastern-cape"}, {"areaCode": 49, "bounds": [[-336.9278, -33.7785], [-334.3577, -31.1904]], "continent": "africa", "country": "south-africa", "subdivision": "eastern-cape"}, {"areaCode": 51, "bounds": [[-335.2038, -31.4853], [-332.3498, -27.8603]], "continent": "africa", "country": "south-africa", "subdivision": "eastern-cape"}]